tweetlytics/__init__.py
tweetlytics/tweetlytics.py
tweetlytics-1.1.1.dist-info/LICENSE
tweetlytics-1.1.1.dist-info/WHEEL
tweetlytics-1.1.1.dist-info/METADATA
tweetlytics-1.1.1.dist-info/RECORD
