Metadata-Version: 2.1
Name: tweetlytics
Version: 1.1.1
Summary: Retrieves tweets on a required topic and timeframe using the official twitter API, stores them as a .json and .csv file, performs data cleaning, data analysis and plotting.
License: MIT
Author: DSCI_524_2022_Group8
Requires-Python: >=3.9,<4.0
Classifier: License :: OSI Approved :: MIT License
Classifier: Programming Language :: Python :: 3
Classifier: Programming Language :: Python :: 3.10
Classifier: Programming Language :: Python :: 3.9
Requires-Dist: altair (>=4.2.0,<5.0.0)
Requires-Dist: altair-saver (>=0.5.0,<0.6.0)
Requires-Dist: arrow (>=1.2.1,<2.0.0)
Requires-Dist: matplotlib (>=3.5.1,<4.0.0)
Requires-Dist: pandas (>=1.3.5,<2.0.0)
Requires-Dist: python-dotenv (>=0.19.2,<0.20.0)
Requires-Dist: requests (>=2.27.1,<3.0.0)
Requires-Dist: textblob (>=0.17.1,<0.18.0)
Requires-Dist: tweepy (>=4.4.0,<5.0.0)
Requires-Dist: wordcloud (>=1.8.1,<2.0.0)
